Metadata-Version: 2.1
Name: loggerholder
Version: 1.0.1
Summary: logger holder
Home-page: https://github.com/wzwjustdoit/loggerholder
Author: wzwjustdoit
Author-email: wzwjustdoit@163.com
Maintainer: wzwjustdoit
Maintainer-email: wzwjustdoit@163.com
License: MIT
Keywords: loggerholder,logger,holder,log
Platform: all
Classifier: License :: OSI Approved :: MIT License
Classifier: Programming Language :: Python
Classifier: Programming Language :: Python :: 3
Classifier: Programming Language :: Python :: 3.6
Classifier: Programming Language :: Python :: Implementation :: CPython
Classifier: Programming Language :: Python :: Implementation :: PyPy
Requires-Python: >=3.0.0
